koladata/__init__.py
koladata/kd.py
koladata/kd_dynamic.py
koladata/kd_ext.py
koladata/kd_types.py
koladata/base/__init__.py
koladata/base/init.so
koladata/base/py_functors_base_py_ext.so
koladata/base/py_conversions/__init__.py
koladata/base/py_conversions/clib.so
koladata/base/py_conversions/dataclasses_util.py
koladata/dynamic_deps/__init__.py
koladata/dynamic_deps/libkoladata_so.so
koladata/expr/__init__.py
koladata/expr/expr_eval.py
koladata/expr/input_container.py
koladata/expr/introspection.py
koladata/expr/py_expr_eval_py_ext.so
koladata/expr/source_location.py
koladata/expr/tracing.py
koladata/expr/tracing_mode.py
koladata/expr/view.py
koladata/ext/__init__.py
koladata/ext/data_slice_webcomponents.js
koladata/ext/data_slice_webcomponents.js.map
koladata/ext/functools.py
koladata/ext/nested_data.py
koladata/ext/npkd.py
koladata/ext/pdkd.py
koladata/ext/py_cloudpickle.py
koladata/ext/vis.py
koladata/ext/contrib/__init__.py
koladata/ext/contrib/functions.py
koladata/ext/contrib/operators.py
koladata/ext/operators/__init__.py
koladata/ext/operators/kde_operators.py
koladata/ext/persisted_data/__init__.py
koladata/ext/persisted_data/bare_root_initial_data_manager.py
koladata/ext/persisted_data/data_slice_manager_interface.py
koladata/ext/persisted_data/data_slice_manager_view.py
koladata/ext/persisted_data/data_slice_path.py
koladata/ext/persisted_data/fs_implementation.py
koladata/ext/persisted_data/fs_interface.py
koladata/ext/persisted_data/fs_util.py
koladata/ext/persisted_data/initial_data_manager_interface.py
koladata/ext/persisted_data/initial_data_manager_registry.py
koladata/ext/persisted_data/persisted_data.py
koladata/ext/persisted_data/persisted_incremental_data_bag_manager.py
koladata/ext/persisted_data/persisted_incremental_data_slice_manager.py
koladata/ext/persisted_data/schema_helper.py
koladata/ext/persisted_data/stubs_and_minimal_bags_lib.py
koladata/ext/persisted_data/value_presence_util.py
koladata/ext/view/__init__.py
koladata-0.0.4.post0.dist-info/METADATA
koladata-0.0.4.post0.dist-info/WHEEL
koladata-0.0.4.post0.dist-info/top_level.txt
koladata-0.0.4.post0.dist-info/RECORD
