Metadata-Version: 2.1
Name: koladata
Version: 0.0.4.post0
Summary: UNKNOWN
Home-page: UNKNOWN
License: UNKNOWN
Platform: UNKNOWN
Requires-Dist: IPython
Requires-Dist: arolla (==0.0.4-0)
Requires-Dist: bidict
Requires-Dist: cloudpickle
Requires-Dist: numpy
Requires-Dist: pandas
